xepor/__init__.py
xepor/xepor.py
xepor-0.6.0.dist-info/LICENSE.txt
xepor-0.6.0.dist-info/METADATA
xepor-0.6.0.dist-info/WHEEL
xepor-0.6.0.dist-info/top_level.txt
xepor-0.6.0.dist-info/RECORD
