Metadata-Version: 2.1
Name: xepor
Version: 0.6.0
Summary: Xepor, a web routing framework for reverse engineers and security researchers.
Home-page: https://github.com/xepor/xepor
Author: ttimasdf
Author-email: opensource@rabit.pw
License: Apache-2.0
Project-URL: Documentation, https://xepor.readthedocs.io/en/latest/index.html
Project-URL: Source, https://github.com/xepor/xepor
Project-URL: Changelog, https://xepor.readthedocs.io/en/latest/changelog.html
Project-URL: Tracker, https://github.com/xepor/xepor/issues
Project-URL: Download, https://pypi.org/project/xepor/#files
Platform: any
Classifier: License :: OSI Approved :: Apache Software License
Classifier: Development Status :: 4 - Beta
Classifier: Operating System :: MacOS
Classifier: Operating System :: POSIX
Classifier: Operating System :: Microsoft :: Windows
Classifier: Programming Language :: Python :: 3 :: Only
Classifier: Programming Language :: Python :: 3.7
Classifier: Programming Language :: Python :: 3.8
Classifier: Programming Language :: Python :: 3.9
Classifier: Programming Language :: Python :: 3.10
Classifier: Programming Language :: Python :: Implementation :: CPython
Classifier: Topic :: Security
Classifier: Topic :: Internet :: WWW/HTTP
Classifier: Topic :: Internet :: Proxy Servers
Classifier: Topic :: System :: Networking :: Monitoring
Classifier: Topic :: Software Development :: Testing
Classifier: Typing :: Typed
Requires-Python: >=3.8
License-File: LICENSE.txt
Requires-Dist: mitmproxy (<10.0.0,>=7.0.0)
Requires-Dist: parse (<2.0.0,>=1.19.0)
Provides-Extra: testing
Requires-Dist: setuptools ; extra == 'testing'
Requires-Dist: pytest ; extra == 'testing'
Requires-Dist: pytest-cov ; extra == 'testing'
Requires-Dist: tox ; extra == 'testing'
